docx2md/__init__.py
docx2md/__main__.py
docx2md/convert.py
docx2md/converter.py
docx2md/docxfile.py
docx2md/docxmedia.py
docx2md/utils.py
docx2md/version.py
docx2md-1.0.5.dist-info/licenses/LICENSE
docx2md-1.0.5.dist-info/METADATA
docx2md-1.0.5.dist-info/WHEEL
docx2md-1.0.5.dist-info/entry_points.txt
docx2md-1.0.5.dist-info/top_level.txt
docx2md-1.0.5.dist-info/RECORD
