Metadata-Version: 2.4
Name: docx2md
Version: 1.0.5
Summary: convert .docx to .md
Author-email: dogatana <dogatana@gmail.com>
Project-URL: Homepage, https://github.com/dogatana/docx2md
Project-URL: Bug Tracker, https://github.com/dogatana/docx2md/issues
Classifier: Programming Language :: Python
Classifier: Programming Language :: Python :: 3
Classifier: Development Status :: 5 - Production/Stable
Classifier: Intended Audience :: Developers
Classifier: Environment :: Other Environment
Classifier: Intended Audience :: Other Audience
Classifier: License :: OSI Approved :: MIT License
Classifier: Operating System :: OS Independent
Classifier: Topic :: Text Editors
Classifier: Topic :: Text Editors :: Documentation
Classifier: Topic :: Text Editors :: Word Processors
Classifier: Topic :: Text Processing
Classifier: Topic :: Text Processing :: Markup
Classifier: Topic :: Text Processing :: Markup :: Markdown
Classifier: Topic :: Utilities
Requires-Python: >=3.10
License-File: LICENSE
Requires-Dist: lxml
Requires-Dist: Pillow
Provides-Extra: dev
Requires-Dist: build; extra == "dev"
Requires-Dist: twine; extra == "dev"
Dynamic: license-file
